{"tel": ["62793001"], "name": ["清华大学 - Tsinghua University"]}
{"tel": ["62799966"], "name": ["清华大学继续教育学院"]}
{"tel": ["62792969"], "name": ["信息公开监督投诉"]}
{"tel": ["62797551"], "name": ["清华大学博士后"]}
{"tel": ["62797255", "62794587"], "name": ["清华大学教育基金会首页"]}
{"tel": ["62795936"], "name": ["清华大学法学院"]}
{"tel": ["62796738"], "name": ["清华大学教育研究院"]}
{"tel": ["62796304"], "name": ["清华大学图书馆"]}
{"tel": ["62797462"], "name": ["清华大学图书馆"]}
{"tel": ["62796704"], "name": ["清华大学图书馆"]}
{"tel": ["6279829", "6279829", "62793", "62795230", "62795230", "62795230"], "name": ["清华大学 - Tsinghua University"]}
{"tel": ["62794718"], "name": ["清华大学科研院"]}
{"tel": ["62792465"], "name": ["清华大学科研院"]}
{"tel": ["62792750"], "name": ["清华大学科研院"]}
{"tel": ["62796025"], "name": ["清华大学科研院"]}
{"tel": ["62792574"], "name": ["清华大学科研院"]}
{"tel": ["62792572"], "name": ["News Of Tsinghua University"]}
{"tel": ["62792587"], "name": ["清华大学图书馆"]}
{"tel": ["62795453"], "name": ["清华大学图书馆"]}
{"tel": ["62794774"], "name": ["清华大学图书馆"]}
{"tel": ["62795857"], "name": ["清华大学图书馆"]}
{"tel": ["62798032"], "name": ["清华大学图书馆"]}
{"tel": ["62798245"], "name": ["清华大学图书馆"]}
{"tel": ["62798821"], "name": ["清华大学图书馆"]}
{"tel": ["62796164"], "name": ["清华大学图书馆"]}
{"tel": ["62798676"], "name": ["联系我们 | 清华大学人文社科图书馆"]}
{"tel": ["62798697"], "name": ["联系我们 | 清华大学人文社科图书馆"]}
{"tel": ["62798547"], "name": ["人文社科图书馆正式开通自助文印服务 | 清华大学人文社科图书馆"]}
{"tel": ["62798676"], "name": ["人文社科图书馆主页于4月19日开通试用 | 清华大学人文社科图书馆"]}
{"tel": ["62797462"], "name": ["2012年外文原版图书展（10月15日至10月19日） | 清华大学人文社科图书馆"]}
{"tel": ["62793001"], "name": ["Tsinghua University"]}
{"tel": ["62797848"], "name": ["清华大学经济管理学院"]}
{"tel": ["62796040"], "name": ["清华大学经济管理学院"]}
{"tel": ["62792988"], "name": ["找回密码 - 清华经管学院"]}
{"tel": ["62791888", "62798086", "62798087"], "name": ["Career Development Center"]}
{"tel": ["62797110"], "name": ["Career Development Center"]}
